gitcommiter/__init__.py
gitcommiter/gitcommiter.py
gitcommiter-0.1.3.dist-info/METADATA
gitcommiter-0.1.3.dist-info/WHEEL
gitcommiter-0.1.3.dist-info/entry_points.txt
gitcommiter-0.1.3.dist-info/licenses/LICENSE
gitcommiter-0.1.3.dist-info/RECORD
