Metadata-Version: 2.3
Name: gitcommiter
Version: 0.1.3
Summary: Automatically add and commit new, modified, and deleted files to Git and write super cool commit messages.
Author-email: SAIKAT KARMAKAR <github.maturity983@passinbox.com>
License: Copyright 2023 Saikat Karmakar
License-File: LICENSE
Keywords: git,python,python3
Classifier: Development Status :: 5 - Production/Stable
Classifier: Programming Language :: Python
Classifier: Programming Language :: Python :: 3.9
Classifier: Programming Language :: Python :: 3.10
Classifier: Programming Language :: Python :: 3.11
Classifier: Programming Language :: Python :: 3.12
Classifier: Programming Language :: Python :: Implementation :: CPython
Classifier: Programming Language :: Python :: Implementation :: PyPy
Requires-Python: >=3.9
Requires-Dist: click>=8.1.7
